ctypeslib/__init__.py
ctypeslib/clang2py.py
ctypeslib/library.py
ctypeslib/codegen/__init__.py
ctypeslib/codegen/clangparser.py
ctypeslib/codegen/codegenerator.py
ctypeslib/codegen/config.py
ctypeslib/codegen/cursorhandler.py
ctypeslib/codegen/handler.py
ctypeslib/codegen/typedesc.py
ctypeslib/codegen/typehandler.py
ctypeslib/codegen/util.py
ctypeslib/data/fundamental_type_name.tpl
ctypeslib/data/headers.tpl
ctypeslib/data/pointer_type.tpl
ctypeslib/data/string_cast.tpl
ctypeslib/data/structure_type.tpl
ctypeslib2_ggml-0.0.1.dist-info/licenses/LICENSE.txt
ctypeslib2_ggml-0.0.1.dist-info/METADATA
ctypeslib2_ggml-0.0.1.dist-info/WHEEL
ctypeslib2_ggml-0.0.1.dist-info/entry_points.txt
ctypeslib2_ggml-0.0.1.dist-info/top_level.txt
ctypeslib2_ggml-0.0.1.dist-info/RECORD
