Metadata-Version: 2.4
Name: ctypeslib2-ggml
Version: 0.0.1
Summary: ctypeslib2 - FFI toolkit, relies on clang
Author-email: Loic Jaquemet <loic.jaquemet+python@gmail.com>, Alex O'Connell <git@alexoconnell.net>
License: License :: OSI Approved :: MIT License
Project-URL: Homepage, https://github.com/acon96/ctypeslib-ggml
Project-URL: Download, https://github.com/acon96/ctypeslib-ggml/releases
Classifier: Development Status :: 5 - Production/Stable
Classifier: Intended Audience :: Developers
Classifier: License :: OSI Approved :: MIT License
Classifier: Programming Language :: Python :: 3.8
Classifier: Topic :: Software Development :: Libraries :: Python Modules
License-File: LICENSE.txt
Requires-Dist: clang>=11
Dynamic: license-file
